{
  "headers": {
    "date": "Fri, 14 Mar 2025 00:00:35 GMT",
    "cross-origin-opener-policy": "same-origin",
    "vary": "Accept-Encoding, Origin",
    "age": "398138",
    "x-amz-cf-id": "y9OaKghsoTLK4TnzMBpsCZ8gsXXAXbdSEzpzkrHKGUH2fpj-5Myuyw==",
    "content-type": "application/typescript; charset=utf-8",
    "accept-ranges": "bytes",
    "cross-origin-resource-policy": "same-origin",
    "cache-control": "public, max-age=31536000, immutable",
    "x-amz-cf-pop": "FRA56-C1",
    "x-amz-version-id": "xmLDpsW3JCCR45JOmgtzi3mkyIrD0sVa",
    "cross-origin-embedder-policy": "same-origin",
    "content-security-policy": "default-src 'none'; style-src 'unsafe-inline'; sandbox",
    "content-length": "87",
    "last-modified": "Fri, 25 Mar 2022 13:32:50 GMT",
    "server-timing": "fetchSource;dur=10",
    "via": "http/2 edgeproxy-h",
    "strict-transport-security": "max-age=63072000; includeSubDomains; preload",
    "x-cache": "Hit from cloudfront",
    "x-amz-replication-status": "COMPLETED",
    "x-content-type-options": "nosniff",
    "referrer-policy": "strict-origin-when-cross-origin",
    "x-frame-options": "DENY",
    "access-control-allow-origin": "*",
    "server": "deno/gcp-europe-west3",
    "etag": "\"fcedf961bc626fd76a0c85089f1afb10\""
  },
  "url": "https://deno.land/std@0.132.0/node/internal_binding/v8.ts",
  "now": {
    "secs_since_epoch": 1742308575,
    "nanos_since_epoch": 527222275
  }
}