{
  "headers": {
    "x-frame-options": "DENY",
    "x-amz-replication-status": "COMPLETED",
    "age": "15643010",
    "content-security-policy": "default-src 'none'; style-src 'unsafe-inline'; sandbox",
    "cross-origin-resource-policy": "same-origin",
    "date": "Wed, 03 May 2023 10:07:14 GMT",
    "x-amz-version-id": "FyrHiTmOtPo4ZFaftXvnjAaQU4eO0pMP",
    "content-length": "675",
    "vary": "Accept-Encoding, Origin",
    "cache-control": "public, max-age=31536000, immutable",
    "x-amz-cf-pop": "ARN56-P2",
    "server": "deno/gcp-europe-north1",
    "cross-origin-opener-policy": "same-origin",
    "last-modified": "Fri, 25 Mar 2022 13:32:48 GMT",
    "x-amz-cf-id": "SvmzgJQXJvzTEEAklVonELpian34DNDDKyK9yyaPulncgKG6ADxjuQ==",
    "x-cache": "Hit from cloudfront",
    "referrer-policy": "strict-origin-when-cross-origin",
    "server-timing": "fetchSource;dur=70",
    "access-control-allow-origin": "*",
    "via": "http/2 edgeproxy-h",
    "accept-ranges": "bytes",
    "cross-origin-embedder-policy": "same-origin",
    "etag": "\"151839e2bba1c1d614d5fcaeccaf2c16\"",
    "content-type": "application/typescript; charset=utf-8",
    "strict-transport-security": "max-age=63072000; includeSubDomains; preload",
    "x-content-type-options": "nosniff"
  },
  "url": "https://deno.land/std@0.132.0/node/_fs/_fs_realpath.ts",
  "now": {
    "secs_since_epoch": 1698751448,
    "nanos_since_epoch": 971363
  }
}