{
  "headers": {
    "x-amz-cf-pop": "FRA56-C1",
    "content-type": "application/javascript",
    "server": "deno/gcp-europe-west3",
    "cross-origin-opener-policy": "same-origin",
    "referrer-policy": "strict-origin-when-cross-origin",
    "strict-transport-security": "max-age=63072000; includeSubDomains; preload",
    "x-amz-version-id": "II3Il3TfeMxAje3.9jtQivT4.x0GBZDl",
    "vary": "Accept-Encoding, Origin",
    "x-cache": "Hit from cloudfront",
    "age": "429944",
    "cross-origin-resource-policy": "same-origin",
    "content-security-policy": "default-src 'none'; style-src 'unsafe-inline'; sandbox",
    "server-timing": "fetchSource;dur=6",
    "access-control-allow-origin": "*",
    "via": "http/2 edgeproxy-h",
    "x-amz-cf-id": "Onz8xg770oeFUe6TYVdIPA_JMnL-xLCxKOoFy2ZEDuDsa02BCsMEKg==",
    "x-amz-replication-status": "COMPLETED",
    "accept-ranges": "bytes",
    "x-frame-options": "DENY",
    "cross-origin-embedder-policy": "same-origin",
    "etag": "W/\"1f9af144e0ab9e36ab84af1fe67024a7\"",
    "cache-control": "public, max-age=31536000, immutable",
    "last-modified": "Fri, 25 Mar 2022 13:32:50 GMT",
    "x-content-type-options": "nosniff",
    "date": "Thu, 13 Mar 2025 15:10:37 GMT"
  },
  "url": "https://deno.land/std@0.132.0/node/internal/crypto/util.mjs",
  "now": {
    "secs_since_epoch": 1742308581,
    "nanos_since_epoch": 942983638
  }
}